hephaestus/__init__.py
hephaestus/hephaestus.cpython-37m-darwin.so
hephaestus/utils.py
hephaestus/walk.py
hephaestus-0.1.1.dist-info/LICENSE
hephaestus-0.1.1.dist-info/METADATA
hephaestus-0.1.1.dist-info/WHEEL
hephaestus-0.1.1.dist-info/top_level.txt
hephaestus-0.1.1.dist-info/RECORD
